{
  "meta": {
    "buildingId": "ve",
    "width": 801,
    "height": 378
  },
  "nodes": [
    {
      "id": "ve 234",
      "type": "room",
      "buildingId": "ve",
      "floor": 2,
      "x": 97,
      "y": 50,
      "label": "ve 234",
      "accessible": true
    },
    {
      "id": "ve 232",
      "type": "room",
      "buildingId": "ve",
      "floor": 2,
      "x": 156,
      "y": 50,
      "label": "ve 232",
      "accessible": true
    },
    {
      "id": "ve 231",
      "type": "room",
      "buildingId": "ve",
      "floor": 2,
      "x": 223,
      "y": 55,
      "label": "ve 232",
      "accessible": true
    },
    {
      "id": "ve 230",
      "type": "room",
      "buildingId": "ve",
      "floor": 2,
      "x": 222,
      "y": 120,
      "label": "ve 230",
      "accessible": true
    },
    {
      "id": "ve 228",
      "type": "room",
      "buildingId": "ve",
      "floor": 2,
      "x": 279,
      "y": 50,
      "label": "ve 228",
      "accessible": true
    },
    {
      "id": "ve 229",
      "type": "room",
      "buildingId": "ve",
      "floor": 2,
      "x": 267,
      "y": 120,
      "label": "ve 229",
      "accessible": true
    },
    {
      "id": "ve 226",
      "type": "room",
      "buildingId": "ve",
      "floor": 2,
      "x": 299,
      "y": 80,
      "label": "ve 226",
      "accessible": true
    },
    {
      "id": "ve 227",
      "type": "room",
      "buildingId": "ve",
      "floor": 2,
      "x": 299,
      "y": 120,
      "label": "ve 227",
      "accessible": true
    },
    {
      "id": "ve 225",
      "type": "room",
      "buildingId": "ve",
      "floor": 2,
      "x": 336,
      "y": 120,
      "label": "ve 225",
      "accessible": true
    },
    {
      "id": "ve 224",
      "type": "room",
      "buildingId": "ve",
      "floor": 2,
      "x": 372,
      "y": 120,
      "label": "ve 224",
      "accessible": true
    },
    {
      "id": "ve 223",
      "type": "room",
      "buildingId": "ve",
      "floor": 2,
      "x": 352,
      "y": 55,
      "label": "ve 223",
      "accessible": true
    },
    {
      "id": "ve 222",
      "type": "room",
      "buildingId": "ve",
      "floor": 2,
      "x": 406,
      "y": 55,
      "label": "ve 222",
      "accessible": true
    },
    {
      "id": "ve 221",
      "type": "room",
      "buildingId": "ve",
      "floor": 2,
      "x": 420,
      "y": 120,
      "label": "ve 221",
      "accessible": true
    },
    {
      "id": "ve 219",
      "type": "room",
      "buildingId": "ve",
      "floor": 2,
      "x": 471,
      "y": 55,
      "label": "ve 219",
      "accessible": true
    },
    {
      "id": "ve 218",
      "type": "room",
      "buildingId": "ve",
      "floor": 2,
      "x": 463,
      "y": 120,
      "label": "ve 218",
      "accessible": true
    },
    {
      "id": "ve 220",
      "type": "room",
      "buildingId": "ve",
      "floor": 2,
      "x": 553,
      "y": 55,
      "label": "ve 220",
      "accessible": true
    },
    {
      "id": "ve 217",
      "type": "room",
      "buildingId": "ve",
      "floor": 2,
      "x": 555,
      "y": 120,
      "label": "ve 217",
      "accessible": true
    },
    {
      "id": "ve 216.2",
      "type": "room",
      "buildingId": "ve",
      "floor": 2,
      "x": 642,
      "y": 50,
      "label": "ve 216.2",
      "accessible": true
    },
    {
      "id": "ve 216.1",
      "type": "room",
      "buildingId": "ve",
      "floor": 2,
      "x": 722,
      "y": 55,
      "label": "ve 216.1",
      "accessible": true
    },
    {
      "id": "214.1",
      "type": "room",
      "buildingId": "ve",
      "floor": 2,
      "x": 775,
      "y": 75,
      "label": "ve 214.1",
      "accessible": true
    },
    {
      "id": "ve 214.2",
      "type": "room",
      "buildingId": "ve",
      "floor": 2,
      "x": 729,
      "y": 120,
      "label": "ve 214.2",
      "accessible": true
    },
    {
      "id": "ve 201",
      "type": "room",
      "buildingId": "ve",
      "floor": 2,
      "x": 88,
      "y": 170,
      "label": "ve 201",
      "accessible": true
    },
    {
      "id": "ve 202.1",
      "type": "room",
      "buildingId": "ve",
      "floor": 2,
      "x": 95,
      "y": 245,
      "label": "ve 202.1",
      "accessible": true
    },
    {
      "id": "ve 202.2",
      "type": "room",
      "buildingId": "ve",
      "floor": 2,
      "x": 131,
      "y": 310,
      "label": "ve 202.2",
      "accessible": true
    },
    {
      "id": "ve 203",
      "type": "room",
      "buildingId": "ve",
      "floor": 2,
      "x": 155,
      "y": 260,
      "label": "ve 203",
      "accessible": true
    },
    {
      "id": "ve 204",
      "type": "room",
      "buildingId": "ve",
      "floor": 2,
      "x": 155,
      "y": 210,
      "label": "ve 204",
      "accessible": true
    },
    {
      "id": "ve 205",
      "type": "room",
      "buildingId": "ve",
      "floor": 2,
      "x": 155,
      "y": 168,
      "label": "ve 205",
      "accessible": true
    },
    {
      "id": "ve 206",
      "type": "room",
      "buildingId": "ve",
      "floor": 2,
      "x": 223,
      "y": 195,
      "label": "ve 206",
      "accessible": true
    },
    {
      "id": "ve 208",
      "type": "room",
      "buildingId": "ve",
      "floor": 2,
      "x": 255,
      "y": 175,
      "label": "ve 208",
      "accessible": true
    },
    {
      "id": "ve 207",
      "type": "room",
      "buildingId": "ve",
      "floor": 2,
      "x": 286,
      "y": 175,
      "label": "ve 207",
      "accessible": true
    },
    {
      "id": "ve 209",
      "type": "room",
      "buildingId": "ve",
      "floor": 2,
      "x": 322,
      "y": 175,
      "label": "ve 209",
      "accessible": true
    },
    {
      "id": "ve 210",
      "type": "room",
      "buildingId": "ve",
      "floor": 2,
      "x": 631,
      "y": 168,
      "label": "ve 210",
      "accessible": true
    },
    {
      "id": "ve 211",
      "type": "room",
      "buildingId": "ve",
      "floor": 2,
      "x": 650,
      "y": 168,
      "label": "ve 211",
      "accessible": true
    },
    {
      "id": "ve 212",
      "type": "room",
      "buildingId": "ve",
      "floor": 2,
      "x": 655,
      "y": 230,
      "label": "ve 212",
      "accessible": true
    },
    {
      "id": "ve 213",
      "type": "room",
      "buildingId": "ve",
      "floor": 2,
      "x": 655,
      "y": 305,
      "label": "ve 213",
      "accessible": true
    },
    {
      "id": "VE2-C1",
      "type": "corridor",
      "buildingId": "ve",
      "floor": 2,
      "x": 95,
      "y": 69,
      "label": "Corridor",
      "accessible": true
    },
    {
      "id": "VE2-C2",
      "type": "corridor",
      "buildingId": "ve",
      "floor": 2,
      "x": 181,
      "y": 74,
      "label": "Corridor",
      "accessible": true
    },
    {
      "id": "VE2-C3",
      "type": "corridor",
      "buildingId": "ve",
      "floor": 2,
      "x": 350,
      "y": 126,
      "label": "Corridor",
      "accessible": true
    },
    {
      "id": "VE2-C4",
      "type": "corridor",
      "buildingId": "ve",
      "floor": 2,
      "x": 470,
      "y": 126,
      "label": "Corridor",
      "accessible": true
    },
    {
      "id": "VE2-C5",
      "type": "corridor",
      "buildingId": "ve",
      "floor": 2,
      "x": 555,
      "y": 126,
      "label": "Corridor",
      "accessible": true
    },
    {
      "id": "VE2-C6",
      "type": "corridor",
      "buildingId": "ve",
      "floor": 2,
      "x": 642,
      "y": 126,
      "label": "Corridor",
      "accessible": true
    },
    {
      "id": "VE2-C7",
      "type": "corridor",
      "buildingId": "ve",
      "floor": 2,
      "x": 759,
      "y": 78,
      "label": "Corridor",
      "accessible": true
    },
    {
      "id": "VE2-C8",
      "type": "corridor",
      "buildingId": "ve",
      "floor": 2,
      "x": 97,
      "y": 140,
      "label": "Corridor",
      "accessible": true
    },
    {
      "id": "VE2-C9",
      "type": "corridor",
      "buildingId": "ve",
      "floor": 2,
      "x": 155,
      "y": 140,
      "label": "Corridor",
      "accessible": true
    },
    {
      "id": "VE2-C10",
      "type": "corridor",
      "buildingId": "ve",
      "floor": 2,
      "x": 222,
      "y": 140,
      "label": "Corridor",
      "accessible": true
    },
    {
      "id": "VE2-C11",
      "type": "corridor",
      "buildingId": "ve",
      "floor": 2,
      "x": 300,
      "y": 140,
      "label": "Corridor",
      "accessible": true
    },
    {
      "id": "VE2-C12",
      "type": "corridor",
      "buildingId": "ve",
      "floor": 2,
      "x": 370,
      "y": 140,
      "label": "Corridor",
      "accessible": true
    },
    {
      "id": "VE2-C13",
      "type": "corridor",
      "buildingId": "ve",
      "floor": 2,
      "x": 420,
      "y": 140,
      "label": "Corridor",
      "accessible": true
    },
    {
      "id": "VE2-C14",
      "type": "corridor",
      "buildingId": "ve",
      "floor": 2,
      "x": 465,
      "y": 140,
      "label": "Corridor",
      "accessible": true
    },
    {
      "id": "VE2-C15",
      "type": "corridor",
      "buildingId": "ve",
      "floor": 2,
      "x": 555,
      "y": 140,
      "label": "Corridor",
      "accessible": true
    },
    {
      "id": "VE2-C16",
      "type": "corridor",
      "buildingId": "ve",
      "floor": 2,
      "x": 631,
      "y": 140,
      "label": "Corridor",
      "accessible": true
    },
    {
      "id": "VE2-C17",
      "type": "corridor",
      "buildingId": "ve",
      "floor": 2,
      "x": 730,
      "y": 140,
      "label": "Corridor",
      "accessible": true
    },
    {
      "id": "VE2-C18",
      "type": "corridor",
      "buildingId": "ve",
      "floor": 2,
      "x": 126,
      "y": 210,
      "label": "Corridor",
      "accessible": true
    },
    {
      "id": "VE2-C19",
      "type": "corridor",
      "buildingId": "ve",
      "floor": 2,
      "x": 126,
      "y": 275,
      "label": "Corridor",
      "accessible": true
    },
    {
      "id": "VE2-C20",
      "type": "corridor",
      "buildingId": "ve",
      "floor": 2,
      "x": 126,
      "y": 305,
      "label": "Corridor",
      "accessible": true
    },
    {
      "id": "VE2-C21",
      "type": "corridor",
      "buildingId": "ve",
      "floor": 2,
      "x": 641,
      "y": 200,
      "label": "Corridor",
      "accessible": true
    },
    {
      "id": "VE2-C22",
      "type": "corridor",
      "buildingId": "ve",
      "floor": 2,
      "x": 641,
      "y": 265,
      "label": "Corridor",
      "accessible": true
    },
    {
      "id": "VE2-C23",
      "type": "corridor",
      "buildingId": "ve",
      "floor": 2,
      "x": 641,
      "y": 320,
      "label": "Corridor",
      "accessible": true
    },
    {
      "id": "VE2-C24",
      "type": "corridor",
      "buildingId": "ve",
      "floor": 2,
      "x": 775,
      "y": 96,
      "label": "Corridor",
      "accessible": true
    },
    {
      "id": "VE2-C25",
      "type": "corridor",
      "buildingId": "ve",
      "floor": 2,
      "x": 240,
      "y": 82,
      "label": "Corridor",
      "accessible": true
    },
    {
      "id": "VE2-C26",
      "type": "corridor",
      "buildingId": "ve",
      "floor": 2,
      "x": 300,
      "y": 82,
      "label": "Corridor",
      "accessible": true
    },
    {
      "id": "VE2-C27",
      "type": "corridor",
      "buildingId": "ve",
      "floor": 2,
      "x": 355,
      "y": 82,
      "label": "Corridor",
      "accessible": true
    },
    {
      "id": "VE2-C28",
      "type": "corridor",
      "buildingId": "ve",
      "floor": 2,
      "x": 410,
      "y": 82,
      "label": "Corridor",
      "accessible": true
    },
    {
      "id": "VE2-C29",
      "type": "corridor",
      "buildingId": "ve",
      "floor": 2,
      "x": 472,
      "y": 82,
      "label": "Corridor",
      "accessible": true
    },
    {
      "id": "VE2-C30",
      "type": "corridor",
      "buildingId": "ve",
      "floor": 2,
      "x": 555,
      "y": 82,
      "label": "Corridor",
      "accessible": true
    },
    {
      "id": "VE2-C31",
      "type": "corridor",
      "buildingId": "ve",
      "floor": 2,
      "x": 642,
      "y": 78,
      "label": "Corridor",
      "accessible": true
    },
    {
      "id": "VE2-C32",
      "type": "corridor",
      "buildingId": "ve",
      "floor": 2,
      "x": 722,
      "y": 78,
      "label": "Corridor",
      "accessible": true
    }
  ],
  "edges": [
    { "from": "VE2-C1", "to": "VE2-C2" },
    { "from": "VE2-C2", "to": "VE2-C25" },
    { "from": "VE2-C25", "to": "VE2-C26" },
    { "from": "VE2-C26", "to": "VE2-C27" },
    { "from": "VE2-C27", "to": "VE2-C28" },
    { "from": "VE2-C28", "to": "VE2-C29" },
    { "from": "VE2-C29", "to": "VE2-C30" },
    { "from": "VE2-C30", "to": "VE2-C31" },
    { "from": "VE2-C31", "to": "VE2-C32" },
    { "from": "VE2-C32", "to": "VE2-C7" },
    { "from": "VE2-C3", "to": "VE2-C4" },
    { "from": "VE2-C4", "to": "VE2-C5" },
    { "from": "VE2-C5", "to": "VE2-C6" },
    { "from": "VE2-C7", "to": "VE2-C24" },
    { "from": "VE2-C1", "to": "VE2-C8" },
    { "from": "VE2-C25", "to": "VE2-C10" },
    { "from": "VE2-C29", "to": "VE2-C4" },
    { "from": "VE2-C30", "to": "VE2-C5" },
    { "from": "VE2-C31", "to": "VE2-C6" },
    { "from": "VE2-C32", "to": "VE2-C17" },
    { "from": "VE2-C5", "to": "VE2-C15" },
    { "from": "VE2-C8", "to": "VE2-C9" },
    { "from": "VE2-C9", "to": "VE2-C10" },
    { "from": "VE2-C10", "to": "VE2-C11" },
    { "from": "VE2-C11", "to": "VE2-C12" },
    { "from": "VE2-C12", "to": "VE2-C13" },
    { "from": "VE2-C13", "to": "VE2-C14" },
    { "from": "VE2-C14", "to": "VE2-C15" },
    { "from": "VE2-C15", "to": "VE2-C16" },
    { "from": "VE2-C16", "to": "VE2-C17" },
    { "from": "VE2-C8", "to": "VE2-C18" },
    { "from": "VE2-C18", "to": "VE2-C19" },
    { "from": "VE2-C19", "to": "VE2-C20" },
    { "from": "VE2-C16", "to": "VE2-C21" },
    { "from": "VE2-C21", "to": "VE2-C22" },
    { "from": "VE2-C22", "to": "VE2-C23" },
    { "from": "ve 234", "to": "VE2-C1" },
    { "from": "ve 232", "to": "VE2-C2" },
    { "from": "ve 231", "to": "VE2-C25" },
    { "from": "ve 228", "to": "VE2-C26" },
    { "from": "ve 223", "to": "VE2-C27" },
    { "from": "ve 222", "to": "VE2-C28" },
    { "from": "ve 219", "to": "VE2-C29" },
    { "from": "ve 220", "to": "VE2-C30" },
    { "from": "ve 216.2", "to": "VE2-C31" },
    { "from": "ve 216.1", "to": "VE2-C32" },
    { "from": "214.1", "to": "VE2-C24" },
    { "from": "ve 230", "to": "VE2-C10" },
    { "from": "ve 229", "to": "VE2-C11" },
    { "from": "ve 226", "to": "VE2-C26" },
    { "from": "ve 227", "to": "VE2-C11" },
    { "from": "ve 225", "to": "VE2-C12" },
    { "from": "ve 224", "to": "VE2-C12" },
    { "from": "ve 221", "to": "VE2-C13" },
    { "from": "ve 218", "to": "VE2-C14" },
    { "from": "ve 217", "to": "VE2-C15" },
    { "from": "ve 214.2", "to": "VE2-C17" },
    { "from": "ve 201", "to": "VE2-C8" },
    { "from": "ve 205", "to": "VE2-C9" },
    { "from": "ve 204", "to": "VE2-C18" },
    { "from": "ve 202.1", "to": "VE2-C19" },
    { "from": "ve 203", "to": "VE2-C19" },
    { "from": "ve 202.2", "to": "VE2-C20" },
    { "from": "ve 206", "to": "VE2-C10" },
    { "from": "ve 208", "to": "VE2-C11" },
    { "from": "ve 207", "to": "VE2-C11" },
    { "from": "ve 209", "to": "VE2-C12" },
    { "from": "ve 210", "to": "VE2-C16" },
    { "from": "ve 211", "to": "VE2-C21" },
    { "from": "ve 212", "to": "VE2-C22" },
    { "from": "ve 213", "to": "VE2-C23" }
  ]
}
